yojn/__init__.py
yojn/main.py
yojn-0.0.2.dist-info/METADATA
yojn-0.0.2.dist-info/WHEEL
yojn-0.0.2.dist-info/top_level.txt
yojn-0.0.2.dist-info/RECORD
