Metadata-Version: 2.1
Name: yojn
Version: 0.0.2
Summary: A package used for yojn installation
Home-page: UNKNOWN
Author: DAO studio
Author-email: <admin@daostudio.in>
License: UNKNOWN
Keywords: python,ai,yojn
Platform: UNKNOWN
Classifier: Development Status :: 1 - Planning
Classifier: Intended Audience :: Developers
Classifier: Programming Language :: Python :: 3
Classifier: Operating System :: Unix
Classifier: Operating System :: MacOS :: MacOS X
Classifier: Operating System :: Microsoft :: Windows
Requires-Dist: requests
